setup.py
cms_client/__init__.py
cms_client/cms_client.py
cms_client/models.py
pullcms_python_client.egg-info/PKG-INFO
pullcms_python_client.egg-info/SOURCES.txt
pullcms_python_client.egg-info/dependency_links.txt
pullcms_python_client.egg-info/top_level.txt
pullcms_python_client.egg-info/zip-safe