Metadata-Version: 1.0
Name: pullcms-python-client
Version: 0.1
Summary: Python API Client for the Pull4Up CMS
Home-page: https://github.com/Pull4up/cms-python-client
Author: Pull4Up
Author-email: fabiano.moraes@pull4up.com
License: MIT
Keywords: pullcms cms python client
Platform: UNKNOWN
